llm_ranking/__init__.py
llm_ranking/eval/__init__.py
llm_ranking/eval/boolean_eval.py
llm_ranking/libs/__init__.py
llm_ranking/libs/llm_models_hub.py
llm_ranking/models/__init__.py
llm_ranking/models/base_test_case.py
llm_ranking/models/boolean_test_case.py
llm_ranking/models/test_result.py
llm_ranking/utils/__init__.py
llm_ranking/utils/boolean_csv_eval.py
llm_ranking/utils/boolean_test_case_reader.py
llm_ranking/utils/gcs_util.py
llm_ranking/utils/gspread_util.py
llm_ranking/utils/langgraph_util.py
llm_ranking/utils/utils.py
botrun_llm_ranking-5.8.25.dist-info/LICENSE
botrun_llm_ranking-5.8.25.dist-info/METADATA
botrun_llm_ranking-5.8.25.dist-info/WHEEL
botrun_llm_ranking-5.8.25.dist-info/RECORD
