Metadata-Version: 2.3
Name: botrun-llm-ranking
Version: 5.8.25
Summary: 
Author: sebastian-hsu
Author-email: sebastian.hsu@gmail.com
Requires-Python: >=3.11,<4.0
Classifier: Programming Language :: Python :: 3
Classifier: Programming Language :: Python :: 3.11
Classifier: Programming Language :: Python :: 3.12
Classifier: Programming Language :: Python :: 3.13
Requires-Dist: aiohttp (>=3.11.9,<4.0.0)
Requires-Dist: anthropic (>=0.40.0,<0.41.0)
Requires-Dist: botrun-ask-folder (>=4.12.171,<5.0.0)
Requires-Dist: botrun-litellm (>=0.2.2,<0.3.0)
Requires-Dist: google-auth (>=2.36.0,<3.0.0)
Requires-Dist: google-cloud-core (>=2.4.1,<3.0.0)
Requires-Dist: google-cloud-storage (>=2.18.2,<3.0.0)
Requires-Dist: langchain-openai (>=0.3.18,<0.4.0)
Requires-Dist: litellm (>=1.53.3,<2.0.0)
Requires-Dist: plotly (>=5.24.1,<6.0.0)
Requires-Dist: pypdf2 (>=3.0.1,<4.0.0)
Requires-Dist: python-dotenv (>=1.0.1,<2.0.0)
Requires-Dist: streamlit (>=1.40.2,<2.0.0)
Requires-Dist: trustcall (>=0.0.39,<0.0.40)
